{
    "signature": "BNDQ",
    "version": "1.3.0",
    "tempo": 134.000000,
    "duration": 16477,
    "durationtime": 153704,
    "samples": [

    ], 
    "tracks": [
        {
            "track": 3, 
            "note": [
                  {"tick": 192, "key": 0, "dur": 0, "isEnd": 0, "toTrack": 0, "volume": 0, "pan": 0, "attr": 0, "time": 1791, "time_dur": 0, "idx": 0},
                  {"tick": 384, "key": 0, "dur": 0, "isEnd": 0, "toTrack": 0, "volume": 0, "pan": 0, "attr": 0, "time": 3582, "time_dur": 0, "idx": 2},
                  {"tick": 576, "key": 0, "dur": 0, "isEnd": 0, "toTrack": 0, "volume": 0, "pan": 0, "attr": 0, "time": 5373, "time_dur": 0, "idx": 4},
                  {"tick": 768, "key": 0, "dur": 0, "isEnd": 0, "toTrack": 0, "volume": 0, "pan": 0, "attr": 0, "time": 7164, "time_dur": 0, "idx": 8},
                  {"tick": 1728, "key": 0, "dur": 48, "isEnd": 1, "toTrack": 3, "volume": 0, "pan": 0, "attr": 3, "time": 16119, "time_dur": 448, "idx": 28},
                  {"tick": 2112, "key": 0, "dur": 0, "isEnd": 0, "toTrack": 0, "volume": 0, "pan": 0, "attr": 0, "time": 19701, "time_dur": 0, "idx": 31},
                  {"tick": 2304, "key": 0, "dur": 0, "isEnd": 0, "toTrack": 0, "volume": 0, "pan": 0, "attr": 0, "time": 21492, "time_dur": 0, "idx": 35},
                  {"tick": 3216, "key": 0, "dur": 0, "isEnd": 0, "toTrack": 0, "volume": 0, "pan": 0, "attr": 0, "time": 30000, "time_dur": 0, "idx": 54},
                  {"tick": 3264, "key": 0, "dur": 96, "isEnd": 1, "toTrack": 3, "volume": 0, "pan": 0, "attr": 3, "time": 30447, "time_dur": 896, "idx": 55},
                  {"tick": 4200, "key": 0, "dur": 120, "isEnd": 1, "toTrack": 3, "volume": 0, "pan": 0, "attr": 3, "time": 39178, "time_dur": 1120, "idx": 64},
                  {"tick": 4968, "key": 0, "dur": 120, "isEnd": 1, "toTrack": 3, "volume": 0, "pan": 0, "attr": 3, "time": 46342, "time_dur": 1119, "idx": 72},
                  {"tick": 5688, "key": 0, "dur": 0, "isEnd": 0, "toTrack": 0, "volume": 0, "pan": 0, "attr": 0, "time": 53058, "time_dur": -1, "idx": 83},
                  {"tick": 6240, "key": 0, "dur": 0, "isEnd": 0, "toTrack": 0, "volume": 0, "pan": 0, "attr": 0, "time": 58208, "time_dur": 0, "idx": 93},
                  {"tick": 6984, "key": 0, "dur": 0, "isEnd": 0, "toTrack": 0, "volume": 0, "pan": 0, "attr": 0, "time": 65148, "time_dur": -1, "idx": 102},
                  {"tick": 7416, "key": 0, "dur": 0, "isEnd": 0, "toTrack": 0, "volume": 0, "pan": 0, "attr": 0, "time": 69178, "time_dur": 0, "idx": 112},
                  {"tick": 8520, "key": 0, "dur": 0, "isEnd": 0, "toTrack": 0, "volume": 0, "pan": 0, "attr": 0, "time": 79476, "time_dur": -1, "idx": 134},
                  {"tick": 8952, "key": 0, "dur": 0, "isEnd": 0, "toTrack": 0, "volume": 0, "pan": 0, "attr": 0, "time": 83506, "time_dur": 0, "idx": 144},
                  {"tick": 10296, "key": 0, "dur": 0, "isEnd": 0, "toTrack": 0, "volume": 0, "pan": 0, "attr": 0, "time": 96043, "time_dur": -1, "idx": 169},
                  {"tick": 10944, "key": 0, "dur": 24, "isEnd": 1, "toTrack": 3, "volume": 0, "pan": 0, "attr": 3, "time": 102089, "time_dur": 223, "idx": 180},
                  {"tick": 11040, "key": 0, "dur": 24, "isEnd": 0, "toTrack": 3, "volume": 0, "pan": 0, "attr": 3, "time": 102985, "time_dur": 223, "idx": 182},
                  {"tick": 11064, "key": 0, "dur": 0, "isEnd": 1, "toTrack": 4, "volume": 0, "pan": 0, "attr": 4, "time": 103208, "time_dur": 1, "idx": 183},
                  {"tick": 11832, "key": 0, "dur": 0, "isEnd": 0, "toTrack": 0, "volume": 0, "pan": 0, "attr": 0, "time": 110372, "time_dur": -1, "idx": 194},
                  {"tick": 12480, "key": 0, "dur": 216, "isEnd": 1, "toTrack": 3, "volume": 0, "pan": 0, "attr": 3, "time": 116417, "time_dur": 2014, "idx": 205},
                  {"tick": 12912, "key": 0, "dur": 192, "isEnd": 1, "toTrack": 3, "volume": 0, "pan": 0, "attr": 3, "time": 120447, "time_dur": 1791, "idx": 208},
                  {"tick": 13992, "key": 0, "dur": 96, "isEnd": 0, "toTrack": 3, "volume": 0, "pan": 0, "attr": 3, "time": 130521, "time_dur": 895, "idx": 215},
                  {"tick": 14088, "key": 0, "dur": 0, "isEnd": 0, "toTrack": 4, "volume": 0, "pan": 0, "attr": 4, "time": 131417, "time_dur": 1, "idx": 216},
                  {"tick": 14400, "key": 0, "dur": 0, "isEnd": 0, "toTrack": 0, "volume": 0, "pan": 0, "attr": 0, "time": 134328, "time_dur": 0, "idx": 218},
                  {"tick": 14592, "key": 0, "dur": 0, "isEnd": 0, "toTrack": 0, "volume": 0, "pan": 0, "attr": 0, "time": 136119, "time_dur": 0, "idx": 222},
                  {"tick": 15552, "key": 0, "dur": 48, "isEnd": 1, "toTrack": 3, "volume": 0, "pan": 0, "attr": 3, "time": 145073, "time_dur": 448, "idx": 242}
            ]
        },
        {
            "track": 4, 
            "note": [
                  {"tick": 672, "key": 0, "dur": 0, "isEnd": 0, "toTrack": 0, "volume": 0, "pan": 0, "attr": 0, "time": 6268, "time_dur": 0, "idx": 6},
                  {"tick": 864, "key": 0, "dur": 0, "isEnd": 0, "toTrack": 0, "volume": 0, "pan": 0, "attr": 0, "time": 8059, "time_dur": 0, "idx": 10},
                  {"tick": 1056, "key": 0, "dur": 0, "isEnd": 0, "toTrack": 0, "volume": 0, "pan": 0, "attr": 0, "time": 9850, "time_dur": 0, "idx": 14},
                  {"tick": 1248, "key": 0, "dur": 0, "isEnd": 0, "toTrack": 0, "volume": 0, "pan": 0, "attr": 0, "time": 11641, "time_dur": 0, "idx": 18},
                  {"tick": 1392, "key": 0, "dur": 0, "isEnd": 0, "toTrack": 0, "volume": 0, "pan": 0, "attr": 0, "time": 12985, "time_dur": 0, "idx": 21},
                  {"tick": 1680, "key": 0, "dur": 0, "isEnd": 0, "toTrack": 0, "volume": 0, "pan": 0, "attr": 0, "time": 15671, "time_dur": 0, "idx": 27},
                  {"tick": 2208, "key": 0, "dur": 0, "isEnd": 0, "toTrack": 0, "volume": 0, "pan": 0, "attr": 0, "time": 20596, "time_dur": 0, "idx": 33},
                  {"tick": 2400, "key": 0, "dur": 0, "isEnd": 0, "toTrack": 0, "volume": 0, "pan": 0, "attr": 0, "time": 22387, "time_dur": 0, "idx": 37},
                  {"tick": 2592, "key": 0, "dur": 0, "isEnd": 0, "toTrack": 0, "volume": 0, "pan": 0, "attr": 0, "time": 24178, "time_dur": 0, "idx": 41},
                  {"tick": 2784, "key": 0, "dur": 0, "isEnd": 0, "toTrack": 0, "volume": 0, "pan": 0, "attr": 0, "time": 25969, "time_dur": 0, "idx": 45},
                  {"tick": 3024, "key": 0, "dur": 0, "isEnd": 0, "toTrack": 0, "volume": 0, "pan": 0, "attr": 0, "time": 28208, "time_dur": 0, "idx": 50},
                  {"tick": 3168, "key": 0, "dur": 0, "isEnd": 0, "toTrack": 0, "volume": 0, "pan": 0, "attr": 0, "time": 29552, "time_dur": 0, "idx": 53},
                  {"tick": 3720, "key": 0, "dur": 0, "isEnd": 0, "toTrack": 0, "volume": 0, "pan": 0, "attr": 0, "time": 34700, "time_dur": -1, "idx": 58},
                  {"tick": 4080, "key": 0, "dur": 0, "isEnd": 0, "toTrack": 0, "volume": 0, "pan": 0, "attr": 0, "time": 38059, "time_dur": 0, "idx": 62},
                  {"tick": 4512, "key": 0, "dur": 0, "isEnd": 0, "toTrack": 0, "volume": 0, "pan": 0, "attr": 0, "time": 42089, "time_dur": 0, "idx": 66},
                  {"tick": 4896, "key": 0, "dur": 0, "isEnd": 0, "toTrack": 0, "volume": 0, "pan": 0, "attr": 0, "time": 45671, "time_dur": 0, "idx": 70},
                  {"tick": 5136, "key": 0, "dur": 0, "isEnd": 0, "toTrack": 0, "volume": 0, "pan": 0, "attr": 0, "time": 47910, "time_dur": 0, "idx": 73},
                  {"tick": 5304, "key": 0, "dur": 0, "isEnd": 0, "toTrack": 0, "volume": 0, "pan": 0, "attr": 0, "time": 49476, "time_dur": -1, "idx": 77},
                  {"tick": 5520, "key": 0, "dur": 0, "isEnd": 0, "toTrack": 0, "volume": 0, "pan": 0, "attr": 0, "time": 51492, "time_dur": 0, "idx": 79},
                  {"tick": 5928, "key": 0, "dur": 0, "isEnd": 0, "toTrack": 0, "volume": 0, "pan": 0, "attr": 0, "time": 55297, "time_dur": -1, "idx": 87},
                  {"tick": 6312, "key": 0, "dur": 168, "isEnd": 1, "toTrack": 4, "volume": 0, "pan": 0, "attr": 3, "time": 58879, "time_dur": 1567, "idx": 95},
                  {"tick": 6792, "key": 0, "dur": 0, "isEnd": 0, "toTrack": 0, "volume": 0, "pan": 0, "attr": 0, "time": 63357, "time_dur": -1, "idx": 97},
                  {"tick": 7032, "key": 0, "dur": 0, "isEnd": 0, "toTrack": 0, "volume": 0, "pan": 0, "attr": 0, "time": 65596, "time_dur": 0, "idx": 104},
                  {"tick": 7176, "key": 0, "dur": 0, "isEnd": 0, "toTrack": 0, "volume": 0, "pan": 0, "attr": 0, "time": 66939, "time_dur": 1, "idx": 107},
                  {"tick": 7296, "key": 0, "dur": 48, "isEnd": 1, "toTrack": 4, "volume": 0, "pan": 0, "attr": 3, "time": 68059, "time_dur": 448, "idx": 111},
                  {"tick": 7464, "key": 0, "dur": 0, "isEnd": 0, "toTrack": 0, "volume": 0, "pan": 0, "attr": 0, "time": 69625, "time_dur": -1, "idx": 114},
                  {"tick": 7608, "key": 0, "dur": 0, "isEnd": 0, "toTrack": 0, "volume": 0, "pan": 0, "attr": 0, "time": 70969, "time_dur": -1, "idx": 117},
                  {"tick": 7752, "key": 0, "dur": 0, "isEnd": 0, "toTrack": 0, "volume": 0, "pan": 0, "attr": 0, "time": 72312, "time_dur": -1, "idx": 120},
                  {"tick": 8040, "key": 0, "dur": 0, "isEnd": 0, "toTrack": 0, "volume": 0, "pan": 0, "attr": 0, "time": 74999, "time_dur": 0, "idx": 126},
                  {"tick": 8328, "key": 0, "dur": 0, "isEnd": 0, "toTrack": 0, "volume": 0, "pan": 0, "attr": 0, "time": 77685, "time_dur": -1, "idx": 129},
                  {"tick": 8568, "key": 0, "dur": 0, "isEnd": 0, "toTrack": 0, "volume": 0, "pan": 0, "attr": 0, "time": 79924, "time_dur": 0, "idx": 136},
                  {"tick": 8712, "key": 0, "dur": 0, "isEnd": 0, "toTrack": 0, "volume": 0, "pan": 0, "attr": 0, "time": 81267, "time_dur": 1, "idx": 139},
                  {"tick": 8832, "key": 0, "dur": 48, "isEnd": 1, "toTrack": 4, "volume": 0, "pan": 0, "attr": 3, "time": 82387, "time_dur": 448, "idx": 143},
                  {"tick": 9000, "key": 0, "dur": 0, "isEnd": 0, "toTrack": 0, "volume": 0, "pan": 0, "attr": 0, "time": 83954, "time_dur": -1, "idx": 146},
                  {"tick": 9144, "key": 0, "dur": 0, "isEnd": 0, "toTrack": 0, "volume": 0, "pan": 0, "attr": 0, "time": 85297, "time_dur": -1, "idx": 149},
                  {"tick": 9288, "key": 0, "dur": 0, "isEnd": 0, "toTrack": 0, "volume": 0, "pan": 0, "attr": 0, "time": 86640, "time_dur": -1, "idx": 152},
                  {"tick": 9648, "key": 0, "dur": 48, "isEnd": 1, "toTrack": 4, "volume": 0, "pan": 0, "attr": 3, "time": 90000, "time_dur": 447, "idx": 160},
                  {"tick": 9912, "key": 0, "dur": 0, "isEnd": 0, "toTrack": 0, "volume": 0, "pan": 0, "attr": 0, "time": 92461, "time_dur": -1, "idx": 164},
                  {"tick": 10512, "key": 0, "dur": 0, "isEnd": 0, "toTrack": 0, "volume": 0, "pan": 0, "attr": 0, "time": 98059, "time_dur": 0, "idx": 171},
                  {"tick": 10656, "key": 0, "dur": 0, "isEnd": 0, "toTrack": 0, "volume": 0, "pan": 0, "attr": 0, "time": 99402, "time_dur": 0, "idx": 174},
                  {"tick": 10800, "key": 0, "dur": 0, "isEnd": 0, "toTrack": 0, "volume": 0, "pan": 0, "attr": 0, "time": 100746, "time_dur": 0, "idx": 177},
                  {"tick": 11160, "key": 0, "dur": 72, "isEnd": 1, "toTrack": 4, "volume": 0, "pan": 0, "attr": 3, "time": 104103, "time_dur": 672, "idx": 185},
                  {"tick": 11448, "key": 0, "dur": 0, "isEnd": 0, "toTrack": 0, "volume": 0, "pan": 0, "attr": 0, "time": 106790, "time_dur": -1, "idx": 189},
                  {"tick": 12048, "key": 0, "dur": 0, "isEnd": 0, "toTrack": 0, "volume": 0, "pan": 0, "attr": 0, "time": 112387, "time_dur": 0, "idx": 196},
                  {"tick": 12228, "key": 0, "dur": 0, "isEnd": 0, "toTrack": 0, "volume": 0, "pan": 0, "attr": 0, "time": 114066, "time_dur": -1, "idx": 200},
                  {"tick": 12336, "key": 0, "dur": 0, "isEnd": 0, "toTrack": 0, "volume": 0, "pan": 0, "attr": 0, "time": 115074, "time_dur": 0, "idx": 202},
                  {"tick": 13224, "key": 0, "dur": 216, "isEnd": 1, "toTrack": 4, "volume": 0, "pan": 0, "attr": 3, "time": 123357, "time_dur": 2015, "idx": 210},
                  {"tick": 13920, "key": 0, "dur": 0, "isEnd": 0, "toTrack": 0, "volume": 0, "pan": 0, "attr": 0, "time": 129850, "time_dur": 0, "idx": 214},
                  {"tick": 14088, "key": 0, "dur": 72, "isEnd": 1, "toTrack": 4, "volume": 0, "pan": 0, "attr": 4, "time": 131417, "time_dur": 672, "idx": 217},
                  {"tick": 14496, "key": 0, "dur": 0, "isEnd": 0, "toTrack": 0, "volume": 0, "pan": 0, "attr": 0, "time": 135223, "time_dur": 0, "idx": 220},
                  {"tick": 14688, "key": 0, "dur": 0, "isEnd": 0, "toTrack": 0, "volume": 0, "pan": 0, "attr": 0, "time": 137014, "time_dur": 0, "idx": 224},
                  {"tick": 14880, "key": 0, "dur": 0, "isEnd": 0, "toTrack": 0, "volume": 0, "pan": 0, "attr": 0, "time": 138805, "time_dur": 0, "idx": 228},
                  {"tick": 15072, "key": 0, "dur": 0, "isEnd": 0, "toTrack": 0, "volume": 0, "pan": 0, "attr": 0, "time": 140596, "time_dur": 0, "idx": 232},
                  {"tick": 15216, "key": 0, "dur": 0, "isEnd": 0, "toTrack": 0, "volume": 0, "pan": 0, "attr": 0, "time": 141939, "time_dur": 0, "idx": 235},
                  {"tick": 15504, "key": 0, "dur": 0, "isEnd": 0, "toTrack": 0, "volume": 0, "pan": 0, "attr": 0, "time": 144626, "time_dur": 0, "idx": 241},
                  {"tick": 15696, "key": 0, "dur": 0, "isEnd": 0, "toTrack": 0, "volume": 0, "pan": 0, "attr": 0, "time": 146417, "time_dur": 0, "idx": 243}
            ]
        },
        {
            "track": 5, 
            "note": [
                  {"tick": 960, "key": 0, "dur": 0, "isEnd": 0, "toTrack": 0, "volume": 0, "pan": 0, "attr": 0, "time": 8955, "time_dur": 0, "idx": 12},
                  {"tick": 1152, "key": 0, "dur": 0, "isEnd": 0, "toTrack": 0, "volume": 0, "pan": 0, "attr": 0, "time": 10746, "time_dur": 0, "idx": 16},
                  {"tick": 1488, "key": 0, "dur": 0, "isEnd": 0, "toTrack": 0, "volume": 0, "pan": 0, "attr": 0, "time": 13880, "time_dur": 0, "idx": 23},
                  {"tick": 1632, "key": 0, "dur": 0, "isEnd": 0, "toTrack": 0, "volume": 0, "pan": 0, "attr": 0, "time": 15223, "time_dur": 0, "idx": 26},
                  {"tick": 1872, "key": 0, "dur": 0, "isEnd": 0, "toTrack": 0, "volume": 0, "pan": 0, "attr": 0, "time": 17462, "time_dur": 0, "idx": 29},
                  {"tick": 2496, "key": 0, "dur": 0, "isEnd": 0, "toTrack": 0, "volume": 0, "pan": 0, "attr": 0, "time": 23283, "time_dur": 0, "idx": 39},
                  {"tick": 2688, "key": 0, "dur": 0, "isEnd": 0, "toTrack": 0, "volume": 0, "pan": 0, "attr": 0, "time": 25074, "time_dur": 0, "idx": 43},
                  {"tick": 2976, "key": 0, "dur": 0, "isEnd": 0, "toTrack": 0, "volume": 0, "pan": 0, "attr": 0, "time": 27761, "time_dur": 0, "idx": 49},
                  {"tick": 3120, "key": 0, "dur": 0, "isEnd": 0, "toTrack": 0, "volume": 0, "pan": 0, "attr": 0, "time": 29104, "time_dur": 0, "idx": 52},
                  {"tick": 3408, "key": 0, "dur": 0, "isEnd": 0, "toTrack": 0, "volume": 0, "pan": 0, "attr": 0, "time": 31790, "time_dur": 0, "idx": 56},
                  {"tick": 3816, "key": 0, "dur": 120, "isEnd": 1, "toTrack": 5, "volume": 0, "pan": 0, "attr": 3, "time": 35596, "time_dur": 1120, "idx": 60},
                  {"tick": 4848, "key": 0, "dur": 0, "isEnd": 0, "toTrack": 0, "volume": 0, "pan": 0, "attr": 0, "time": 45223, "time_dur": 0, "idx": 69},
                  {"tick": 5232, "key": 0, "dur": 0, "isEnd": 0, "toTrack": 0, "volume": 0, "pan": 0, "attr": 0, "time": 48805, "time_dur": 0, "idx": 75},
                  {"tick": 5664, "key": 0, "dur": 0, "isEnd": 0, "toTrack": 0, "volume": 0, "pan": 0, "attr": 0, "time": 52835, "time_dur": 0, "idx": 82},
                  {"tick": 6000, "key": 0, "dur": 0, "isEnd": 0, "toTrack": 0, "volume": 0, "pan": 0, "attr": 0, "time": 55970, "time_dur": 0, "idx": 89},
                  {"tick": 6192, "key": 0, "dur": 0, "isEnd": 0, "toTrack": 0, "volume": 0, "pan": 0, "attr": 0, "time": 57761, "time_dur": 0, "idx": 92},
                  {"tick": 6840, "key": 0, "dur": 0, "isEnd": 0, "toTrack": 0, "volume": 0, "pan": 0, "attr": 0, "time": 63805, "time_dur": 0, "idx": 99},
                  {"tick": 7008, "key": 0, "dur": 0, "isEnd": 0, "toTrack": 0, "volume": 0, "pan": 0, "attr": 0, "time": 65373, "time_dur": 0, "idx": 103},
                  {"tick": 7104, "key": 0, "dur": 48, "isEnd": 1, "toTrack": 5, "volume": 0, "pan": 0, "attr": 3, "time": 66268, "time_dur": 448, "idx": 106},
                  {"tick": 7224, "key": 0, "dur": 0, "isEnd": 0, "toTrack": 0, "volume": 0, "pan": 0, "attr": 0, "time": 67387, "time_dur": 0, "idx": 109},
                  {"tick": 7800, "key": 0, "dur": 0, "isEnd": 0, "toTrack": 0, "volume": 0, "pan": 0, "attr": 0, "time": 72760, "time_dur": -1, "idx": 122},
                  {"tick": 7872, "key": 0, "dur": 48, "isEnd": 1, "toTrack": 5, "volume": 0, "pan": 0, "attr": 3, "time": 73432, "time_dur": 448, "idx": 124},
                  {"tick": 8376, "key": 0, "dur": 0, "isEnd": 0, "toTrack": 0, "volume": 0, "pan": 0, "attr": 0, "time": 78133, "time_dur": 0, "idx": 131},
                  {"tick": 8640, "key": 0, "dur": 48, "isEnd": 1, "toTrack": 5, "volume": 0, "pan": 0, "attr": 3, "time": 80596, "time_dur": 448, "idx": 138},
                  {"tick": 8760, "key": 0, "dur": 0, "isEnd": 0, "toTrack": 0, "volume": 0, "pan": 0, "attr": 0, "time": 81715, "time_dur": 0, "idx": 141},
                  {"tick": 9336, "key": 0, "dur": 0, "isEnd": 0, "toTrack": 0, "volume": 0, "pan": 0, "attr": 0, "time": 87088, "time_dur": -1, "idx": 154},
                  {"tick": 9408, "key": 0, "dur": 48, "isEnd": 1, "toTrack": 5, "volume": 0, "pan": 0, "attr": 3, "time": 87760, "time_dur": 448, "idx": 156},
                  {"tick": 9576, "key": 0, "dur": 0, "isEnd": 0, "toTrack": 0, "volume": 0, "pan": 0, "attr": 0, "time": 89327, "time_dur": 0, "idx": 158},
                  {"tick": 9960, "key": 0, "dur": 72, "isEnd": 1, "toTrack": 5, "volume": 0, "pan": 0, "attr": 3, "time": 92909, "time_dur": 672, "idx": 165},
                  {"tick": 10272, "key": 0, "dur": 0, "isEnd": 0, "toTrack": 0, "volume": 0, "pan": 0, "attr": 0, "time": 95820, "time_dur": 0, "idx": 168},
                  {"tick": 10680, "key": 0, "dur": 0, "isEnd": 0, "toTrack": 0, "volume": 0, "pan": 0, "attr": 0, "time": 99625, "time_dur": -1, "idx": 175},
                  {"tick": 10896, "key": 0, "dur": 0, "isEnd": 0, "toTrack": 0, "volume": 0, "pan": 0, "attr": 0, "time": 101641, "time_dur": 0, "idx": 179},
                  {"tick": 11424, "key": 0, "dur": 0, "isEnd": 0, "toTrack": 0, "volume": 0, "pan": 0, "attr": 0, "time": 106566, "time_dur": 0, "idx": 188},
                  {"tick": 11496, "key": 0, "dur": 72, "isEnd": 1, "toTrack": 5, "volume": 0, "pan": 0, "attr": 3, "time": 107237, "time_dur": 672, "idx": 190},
                  {"tick": 11808, "key": 0, "dur": 0, "isEnd": 0, "toTrack": 0, "volume": 0, "pan": 0, "attr": 0, "time": 110148, "time_dur": 0, "idx": 193},
                  {"tick": 12192, "key": 0, "dur": 0, "isEnd": 0, "toTrack": 0, "volume": 0, "pan": 0, "attr": 0, "time": 113731, "time_dur": 0, "idx": 199},
                  {"tick": 12432, "key": 0, "dur": 0, "isEnd": 0, "toTrack": 0, "volume": 0, "pan": 0, "attr": 0, "time": 115969, "time_dur": 0, "idx": 204},
                  {"tick": 13824, "key": 0, "dur": 0, "isEnd": 0, "toTrack": 0, "volume": 0, "pan": 0, "attr": 0, "time": 128955, "time_dur": 0, "idx": 213},
                  {"tick": 14784, "key": 0, "dur": 0, "isEnd": 0, "toTrack": 0, "volume": 0, "pan": 0, "attr": 0, "time": 137909, "time_dur": 0, "idx": 226},
                  {"tick": 14976, "key": 0, "dur": 0, "isEnd": 0, "toTrack": 0, "volume": 0, "pan": 0, "attr": 0, "time": 139700, "time_dur": 0, "idx": 230},
                  {"tick": 15312, "key": 0, "dur": 0, "isEnd": 0, "toTrack": 0, "volume": 0, "pan": 0, "attr": 0, "time": 142835, "time_dur": 0, "idx": 237},
                  {"tick": 15456, "key": 0, "dur": 0, "isEnd": 0, "toTrack": 0, "volume": 0, "pan": 0, "attr": 0, "time": 144178, "time_dur": 0, "idx": 240}
            ]
        },
        {
            "track": 6, 
            "note": [
                  {"tick": 288, "key": 0, "dur": 0, "isEnd": 1, "toTrack": 7, "volume": 0, "pan": 0, "attr": 3, "time": 2686, "time_dur": 1, "idx": 1},
                  {"tick": 480, "key": 0, "dur": 0, "isEnd": 1, "toTrack": 7, "volume": 0, "pan": 0, "attr": 3, "time": 4477, "time_dur": 1, "idx": 3},
                  {"tick": 720, "key": 0, "dur": 0, "isEnd": 0, "toTrack": 0, "volume": 0, "pan": 0, "attr": 0, "time": 6716, "time_dur": 0, "idx": 7},
                  {"tick": 912, "key": 0, "dur": 0, "isEnd": 0, "toTrack": 0, "volume": 0, "pan": 0, "attr": 0, "time": 8507, "time_dur": 0, "idx": 11},
                  {"tick": 1104, "key": 0, "dur": 0, "isEnd": 0, "toTrack": 0, "volume": 0, "pan": 0, "attr": 0, "time": 10298, "time_dur": 0, "idx": 15},
                  {"tick": 1296, "key": 0, "dur": 0, "isEnd": 0, "toTrack": 0, "volume": 0, "pan": 0, "attr": 0, "time": 12089, "time_dur": 0, "idx": 19},
                  {"tick": 1440, "key": 0, "dur": 0, "isEnd": 0, "toTrack": 0, "volume": 0, "pan": 0, "attr": 0, "time": 13432, "time_dur": 0, "idx": 22},
                  {"tick": 1584, "key": 0, "dur": 0, "isEnd": 0, "toTrack": 0, "volume": 0, "pan": 0, "attr": 0, "time": 14776, "time_dur": 0, "idx": 25},
                  {"tick": 1920, "key": 0, "dur": 48, "isEnd": 1, "toTrack": 6, "volume": 0, "pan": 0, "attr": 3, "time": 17910, "time_dur": 448, "idx": 30},
                  {"tick": 2256, "key": 0, "dur": 0, "isEnd": 0, "toTrack": 0, "volume": 0, "pan": 0, "attr": 0, "time": 21044, "time_dur": 0, "idx": 34},
                  {"tick": 2448, "key": 0, "dur": 0, "isEnd": 0, "toTrack": 0, "volume": 0, "pan": 0, "attr": 0, "time": 22835, "time_dur": 0, "idx": 38},
                  {"tick": 2640, "key": 0, "dur": 0, "isEnd": 0, "toTrack": 0, "volume": 0, "pan": 0, "attr": 0, "time": 24626, "time_dur": 0, "idx": 42},
                  {"tick": 2832, "key": 0, "dur": 0, "isEnd": 0, "toTrack": 0, "volume": 0, "pan": 0, "attr": 0, "time": 26417, "time_dur": 0, "idx": 46},
                  {"tick": 2928, "key": 0, "dur": 0, "isEnd": 0, "toTrack": 0, "volume": 0, "pan": 0, "attr": 0, "time": 27313, "time_dur": 0, "idx": 48},
                  {"tick": 3072, "key": 0, "dur": 0, "isEnd": 0, "toTrack": 0, "volume": 0, "pan": 0, "attr": 0, "time": 28656, "time_dur": 0, "idx": 51},
                  {"tick": 3744, "key": 0, "dur": 0, "isEnd": 0, "toTrack": 0, "volume": 0, "pan": 0, "attr": 0, "time": 34925, "time_dur": 0, "idx": 59},
                  {"tick": 4128, "key": 0, "dur": 0, "isEnd": 0, "toTrack": 0, "volume": 0, "pan": 0, "attr": 0, "time": 38507, "time_dur": 0, "idx": 63},
                  {"tick": 4584, "key": 0, "dur": 120, "isEnd": 1, "toTrack": 6, "volume": 0, "pan": 0, "attr": 3, "time": 42760, "time_dur": 1119, "idx": 67},
                  {"tick": 4920, "key": 0, "dur": 0, "isEnd": 0, "toTrack": 0, "volume": 0, "pan": 0, "attr": 0, "time": 45894, "time_dur": -1, "idx": 71},
                  {"tick": 5184, "key": 0, "dur": 0, "isEnd": 0, "toTrack": 0, "volume": 0, "pan": 0, "attr": 0, "time": 48358, "time_dur": 0, "idx": 74},
                  {"tick": 5352, "key": 0, "dur": 120, "isEnd": 1, "toTrack": 6, "volume": 0, "pan": 0, "attr": 3, "time": 49924, "time_dur": 1119, "idx": 78},
                  {"tick": 5568, "key": 0, "dur": 0, "isEnd": 0, "toTrack": 0, "volume": 0, "pan": 0, "attr": 0, "time": 51940, "time_dur": 0, "idx": 80},
                  {"tick": 5616, "key": 0, "dur": 0, "isEnd": 0, "toTrack": 0, "volume": 0, "pan": 0, "attr": 0, "time": 52388, "time_dur": 0, "idx": 81},
                  {"tick": 5736, "key": 0, "dur": 24, "isEnd": 0, "toTrack": 6, "volume": 0, "pan": 0, "attr": 3, "time": 53506, "time_dur": 224, "idx": 84},
                  {"tick": 5760, "key": 0, "dur": 0, "isEnd": 0, "toTrack": 7, "volume": 0, "pan": 0, "attr": 4, "time": 53731, "time_dur": 1, "idx": 85},
                  {"tick": 5952, "key": 0, "dur": 0, "isEnd": 0, "toTrack": 0, "volume": 0, "pan": 0, "attr": 0, "time": 55522, "time_dur": 0, "idx": 88},
                  {"tick": 6144, "key": 0, "dur": 0, "isEnd": 0, "toTrack": 0, "volume": 0, "pan": 0, "attr": 0, "time": 57313, "time_dur": 0, "idx": 91},
                  {"tick": 6264, "key": 0, "dur": 0, "isEnd": 0, "toTrack": 0, "volume": 0, "pan": 0, "attr": 0, "time": 58431, "time_dur": -1, "idx": 94},
                  {"tick": 6816, "key": 0, "dur": 0, "isEnd": 0, "toTrack": 0, "volume": 0, "pan": 0, "attr": 0, "time": 63582, "time_dur": 0, "idx": 98},
                  {"tick": 6912, "key": 0, "dur": 48, "isEnd": 1, "toTrack": 6, "volume": 0, "pan": 0, "attr": 3, "time": 64477, "time_dur": 448, "idx": 101},
                  {"tick": 7056, "key": 0, "dur": 0, "isEnd": 0, "toTrack": 0, "volume": 0, "pan": 0, "attr": 0, "time": 65820, "time_dur": 0, "idx": 105},
                  {"tick": 7248, "key": 0, "dur": 0, "isEnd": 0, "toTrack": 0, "volume": 0, "pan": 0, "attr": 0, "time": 67611, "time_dur": 0, "idx": 110},
                  {"tick": 7440, "key": 0, "dur": 0, "isEnd": 0, "toTrack": 0, "volume": 0, "pan": 0, "attr": 0, "time": 69402, "time_dur": 0, "idx": 113},
                  {"tick": 7584, "key": 0, "dur": 0, "isEnd": 0, "toTrack": 0, "volume": 0, "pan": 0, "attr": 0, "time": 70746, "time_dur": 0, "idx": 116},
                  {"tick": 7680, "key": 0, "dur": 48, "isEnd": 1, "toTrack": 6, "volume": 0, "pan": 0, "attr": 3, "time": 71641, "time_dur": 448, "idx": 119},
                  {"tick": 7776, "key": 0, "dur": 0, "isEnd": 0, "toTrack": 0, "volume": 0, "pan": 0, "attr": 0, "time": 72537, "time_dur": 0, "idx": 121},
                  {"tick": 8064, "key": 0, "dur": 96, "isEnd": 1, "toTrack": 6, "volume": 0, "pan": 0, "attr": 3, "time": 75223, "time_dur": 896, "idx": 127},
                  {"tick": 8352, "key": 0, "dur": 0, "isEnd": 0, "toTrack": 0, "volume": 0, "pan": 0, "attr": 0, "time": 77910, "time_dur": 0, "idx": 130},
                  {"tick": 8448, "key": 0, "dur": 48, "isEnd": 1, "toTrack": 6, "volume": 0, "pan": 0, "attr": 3, "time": 78805, "time_dur": 448, "idx": 133},
                  {"tick": 8544, "key": 0, "dur": 0, "isEnd": 0, "toTrack": 0, "volume": 0, "pan": 0, "attr": 0, "time": 79701, "time_dur": 0, "idx": 135},
                  {"tick": 8784, "key": 0, "dur": 0, "isEnd": 0, "toTrack": 0, "volume": 0, "pan": 0, "attr": 0, "time": 81940, "time_dur": 0, "idx": 142},
                  {"tick": 8976, "key": 0, "dur": 0, "isEnd": 0, "toTrack": 0, "volume": 0, "pan": 0, "attr": 0, "time": 83730, "time_dur": 0, "idx": 145},
                  {"tick": 9120, "key": 0, "dur": 0, "isEnd": 0, "toTrack": 0, "volume": 0, "pan": 0, "attr": 0, "time": 85074, "time_dur": 0, "idx": 148},
                  {"tick": 9216, "key": 0, "dur": 48, "isEnd": 1, "toTrack": 6, "volume": 0, "pan": 0, "attr": 3, "time": 85969, "time_dur": 448, "idx": 151},
                  {"tick": 9312, "key": 0, "dur": 0, "isEnd": 0, "toTrack": 0, "volume": 0, "pan": 0, "attr": 0, "time": 86865, "time_dur": 0, "idx": 153},
                  {"tick": 9600, "key": 0, "dur": 0, "isEnd": 0, "toTrack": 0, "volume": 0, "pan": 0, "attr": 0, "time": 89552, "time_dur": 0, "idx": 159},
                  {"tick": 9888, "key": 0, "dur": 0, "isEnd": 0, "toTrack": 0, "volume": 0, "pan": 0, "attr": 0, "time": 92238, "time_dur": 0, "idx": 163},
                  {"tick": 10344, "key": 0, "dur": 72, "isEnd": 1, "toTrack": 6, "volume": 0, "pan": 0, "attr": 3, "time": 96491, "time_dur": 672, "idx": 170},
                  {"tick": 10560, "key": 0, "dur": 0, "isEnd": 0, "toTrack": 0, "volume": 0, "pan": 0, "attr": 0, "time": 98507, "time_dur": 0, "idx": 172},
                  {"tick": 10608, "key": 0, "dur": 0, "isEnd": 0, "toTrack": 0, "volume": 0, "pan": 0, "attr": 0, "time": 98955, "time_dur": 0, "idx": 173},
                  {"tick": 10848, "key": 0, "dur": 0, "isEnd": 0, "toTrack": 0, "volume": 0, "pan": 0, "attr": 0, "time": 101194, "time_dur": 0, "idx": 178},
                  {"tick": 11112, "key": 0, "dur": 0, "isEnd": 0, "toTrack": 0, "volume": 0, "pan": 0, "attr": 0, "time": 103655, "time_dur": -1, "idx": 184},
                  {"tick": 11328, "key": 0, "dur": 0, "isEnd": 0, "toTrack": 0, "volume": 0, "pan": 0, "attr": 0, "time": 105671, "time_dur": 0, "idx": 186},
                  {"tick": 11376, "key": 0, "dur": 0, "isEnd": 0, "toTrack": 0, "volume": 0, "pan": 0, "attr": 0, "time": 106119, "time_dur": 0, "idx": 187},
                  {"tick": 11880, "key": 0, "dur": 72, "isEnd": 1, "toTrack": 6, "volume": 0, "pan": 0, "attr": 3, "time": 110820, "time_dur": 672, "idx": 195},
                  {"tick": 12096, "key": 0, "dur": 0, "isEnd": 0, "toTrack": 0, "volume": 0, "pan": 0, "attr": 0, "time": 112835, "time_dur": 0, "idx": 197},
                  {"tick": 12144, "key": 0, "dur": 0, "isEnd": 0, "toTrack": 0, "volume": 0, "pan": 0, "attr": 0, "time": 113283, "time_dur": 0, "idx": 198},
                  {"tick": 12384, "key": 0, "dur": 0, "isEnd": 0, "toTrack": 0, "volume": 0, "pan": 0, "attr": 0, "time": 115522, "time_dur": 0, "idx": 203},
                  {"tick": 12792, "key": 0, "dur": 72, "isEnd": 1, "toTrack": 6, "volume": 0, "pan": 0, "attr": 3, "time": 119327, "time_dur": 672, "idx": 207},
                  {"tick": 13728, "key": 0, "dur": 0, "isEnd": 0, "toTrack": 0, "volume": 0, "pan": 0, "attr": 0, "time": 128059, "time_dur": 0, "idx": 212},
                  {"tick": 14544, "key": 0, "dur": 0, "isEnd": 0, "toTrack": 0, "volume": 0, "pan": 0, "attr": 0, "time": 135671, "time_dur": 0, "idx": 221},
                  {"tick": 14736, "key": 0, "dur": 0, "isEnd": 0, "toTrack": 0, "volume": 0, "pan": 0, "attr": 0, "time": 137462, "time_dur": 0, "idx": 225},
                  {"tick": 14928, "key": 0, "dur": 0, "isEnd": 0, "toTrack": 0, "volume": 0, "pan": 0, "attr": 0, "time": 139253, "time_dur": 0, "idx": 229},
                  {"tick": 15120, "key": 0, "dur": 0, "isEnd": 0, "toTrack": 0, "volume": 0, "pan": 0, "attr": 0, "time": 141044, "time_dur": 0, "idx": 233},
                  {"tick": 15264, "key": 0, "dur": 0, "isEnd": 0, "toTrack": 0, "volume": 0, "pan": 0, "attr": 0, "time": 142387, "time_dur": 0, "idx": 236},
                  {"tick": 15408, "key": 0, "dur": 0, "isEnd": 0, "toTrack": 0, "volume": 0, "pan": 0, "attr": 0, "time": 143730, "time_dur": 0, "idx": 239},
                  {"tick": 15744, "key": 0, "dur": 48, "isEnd": 1, "toTrack": 6, "volume": 0, "pan": 0, "attr": 3, "time": 146864, "time_dur": 448, "idx": 244}
            ]
        },
        {
            "track": 7, 
            "note": [
                  {"tick": 624, "key": 0, "dur": 0, "isEnd": 0, "toTrack": 0, "volume": 0, "pan": 0, "attr": 0, "time": 5820, "time_dur": 0, "idx": 5},
                  {"tick": 816, "key": 0, "dur": 0, "isEnd": 0, "toTrack": 0, "volume": 0, "pan": 0, "attr": 0, "time": 7611, "time_dur": 0, "idx": 9},
                  {"tick": 1008, "key": 0, "dur": 0, "isEnd": 0, "toTrack": 0, "volume": 0, "pan": 0, "attr": 0, "time": 9402, "time_dur": 0, "idx": 13},
                  {"tick": 1200, "key": 0, "dur": 0, "isEnd": 0, "toTrack": 0, "volume": 0, "pan": 0, "attr": 0, "time": 11193, "time_dur": 0, "idx": 17},
                  {"tick": 1344, "key": 0, "dur": 0, "isEnd": 0, "toTrack": 0, "volume": 0, "pan": 0, "attr": 0, "time": 12537, "time_dur": 0, "idx": 20},
                  {"tick": 1536, "key": 0, "dur": 0, "isEnd": 0, "toTrack": 0, "volume": 0, "pan": 0, "attr": 0, "time": 14328, "time_dur": 0, "idx": 24},
                  {"tick": 2160, "key": 0, "dur": 0, "isEnd": 0, "toTrack": 0, "volume": 0, "pan": 0, "attr": 0, "time": 20148, "time_dur": 0, "idx": 32},
                  {"tick": 2352, "key": 0, "dur": 0, "isEnd": 0, "toTrack": 0, "volume": 0, "pan": 0, "attr": 0, "time": 21939, "time_dur": 0, "idx": 36},
                  {"tick": 2544, "key": 0, "dur": 0, "isEnd": 0, "toTrack": 0, "volume": 0, "pan": 0, "attr": 0, "time": 23730, "time_dur": 0, "idx": 40},
                  {"tick": 2736, "key": 0, "dur": 0, "isEnd": 0, "toTrack": 0, "volume": 0, "pan": 0, "attr": 0, "time": 25521, "time_dur": 0, "idx": 44},
                  {"tick": 2880, "key": 0, "dur": 0, "isEnd": 0, "toTrack": 0, "volume": 0, "pan": 0, "attr": 0, "time": 26865, "time_dur": 0, "idx": 47},
                  {"tick": 3456, "key": 0, "dur": 96, "isEnd": 1, "toTrack": 7, "volume": 0, "pan": 0, "attr": 3, "time": 32238, "time_dur": 896, "idx": 57},
                  {"tick": 4032, "key": 0, "dur": 0, "isEnd": 0, "toTrack": 0, "volume": 0, "pan": 0, "attr": 0, "time": 37611, "time_dur": 0, "idx": 61},
                  {"tick": 4488, "key": 0, "dur": 0, "isEnd": 0, "toTrack": 0, "volume": 0, "pan": 0, "attr": 0, "time": 41864, "time_dur": -1, "idx": 65},
                  {"tick": 4800, "key": 0, "dur": 0, "isEnd": 0, "toTrack": 0, "volume": 0, "pan": 0, "attr": 0, "time": 44776, "time_dur": 0, "idx": 68},
                  {"tick": 5280, "key": 0, "dur": 0, "isEnd": 0, "toTrack": 0, "volume": 0, "pan": 0, "attr": 0, "time": 49253, "time_dur": 0, "idx": 76},
                  {"tick": 5760, "key": 0, "dur": 96, "isEnd": 1, "toTrack": 7, "volume": 0, "pan": 0, "attr": 4, "time": 53731, "time_dur": 895, "idx": 86},
                  {"tick": 6024, "key": 0, "dur": 0, "isEnd": 0, "toTrack": 0, "volume": 0, "pan": 0, "attr": 0, "time": 56193, "time_dur": 0, "idx": 90},
                  {"tick": 6720, "key": 0, "dur": 48, "isEnd": 1, "toTrack": 7, "volume": 0, "pan": 0, "attr": 3, "time": 62686, "time_dur": 448, "idx": 96},
                  {"tick": 6864, "key": 0, "dur": 0, "isEnd": 0, "toTrack": 0, "volume": 0, "pan": 0, "attr": 0, "time": 64029, "time_dur": 0, "idx": 100},
                  {"tick": 7200, "key": 0, "dur": 0, "isEnd": 0, "toTrack": 0, "volume": 0, "pan": 0, "attr": 0, "time": 67164, "time_dur": 0, "idx": 108},
                  {"tick": 7488, "key": 0, "dur": 48, "isEnd": 1, "toTrack": 7, "volume": 0, "pan": 0, "attr": 3, "time": 69850, "time_dur": 448, "idx": 115},
                  {"tick": 7632, "key": 0, "dur": 0, "isEnd": 0, "toTrack": 0, "volume": 0, "pan": 0, "attr": 0, "time": 71194, "time_dur": 0, "idx": 118},
                  {"tick": 7824, "key": 0, "dur": 0, "isEnd": 0, "toTrack": 0, "volume": 0, "pan": 0, "attr": 0, "time": 72985, "time_dur": 0, "idx": 123},
                  {"tick": 8016, "key": 0, "dur": 0, "isEnd": 0, "toTrack": 0, "volume": 0, "pan": 0, "attr": 0, "time": 74776, "time_dur": 0, "idx": 125},
                  {"tick": 8256, "key": 0, "dur": 48, "isEnd": 1, "toTrack": 7, "volume": 0, "pan": 0, "attr": 3, "time": 77014, "time_dur": 448, "idx": 128},
                  {"tick": 8400, "key": 0, "dur": 0, "isEnd": 0, "toTrack": 0, "volume": 0, "pan": 0, "attr": 0, "time": 78357, "time_dur": 0, "idx": 132},
                  {"tick": 8592, "key": 0, "dur": 0, "isEnd": 0, "toTrack": 0, "volume": 0, "pan": 0, "attr": 0, "time": 80148, "time_dur": 0, "idx": 137},
                  {"tick": 8736, "key": 0, "dur": 0, "isEnd": 0, "toTrack": 0, "volume": 0, "pan": 0, "attr": 0, "time": 81492, "time_dur": 0, "idx": 140},
                  {"tick": 9024, "key": 0, "dur": 48, "isEnd": 1, "toTrack": 7, "volume": 0, "pan": 0, "attr": 3, "time": 84178, "time_dur": 448, "idx": 147},
                  {"tick": 9168, "key": 0, "dur": 0, "isEnd": 0, "toTrack": 0, "volume": 0, "pan": 0, "attr": 0, "time": 85522, "time_dur": 0, "idx": 150},
                  {"tick": 9360, "key": 0, "dur": 0, "isEnd": 0, "toTrack": 0, "volume": 0, "pan": 0, "attr": 0, "time": 87313, "time_dur": 0, "idx": 155},
                  {"tick": 9552, "key": 0, "dur": 0, "isEnd": 0, "toTrack": 0, "volume": 0, "pan": 0, "attr": 0, "time": 89104, "time_dur": 0, "idx": 157},
                  {"tick": 9792, "key": 0, "dur": 0, "isEnd": 0, "toTrack": 0, "volume": 0, "pan": 0, "attr": 0, "time": 91343, "time_dur": 0, "idx": 161},
                  {"tick": 9840, "key": 0, "dur": 0, "isEnd": 0, "toTrack": 0, "volume": 0, "pan": 0, "attr": 0, "time": 91791, "time_dur": 0, "idx": 162},
                  {"tick": 10176, "key": 0, "dur": 0, "isEnd": 0, "toTrack": 0, "volume": 0, "pan": 0, "attr": 0, "time": 94925, "time_dur": 0, "idx": 166},
                  {"tick": 10224, "key": 0, "dur": 0, "isEnd": 0, "toTrack": 0, "volume": 0, "pan": 0, "attr": 0, "time": 95373, "time_dur": 0, "idx": 167},
                  {"tick": 10728, "key": 0, "dur": 48, "isEnd": 1, "toTrack": 7, "volume": 0, "pan": 0, "attr": 3, "time": 100073, "time_dur": 447, "idx": 176},
                  {"tick": 10992, "key": 0, "dur": 24, "isEnd": 1, "toTrack": 7, "volume": 0, "pan": 0, "attr": 3, "time": 102537, "time_dur": 223, "idx": 181},
                  {"tick": 11712, "key": 0, "dur": 0, "isEnd": 0, "toTrack": 0, "volume": 0, "pan": 0, "attr": 0, "time": 109253, "time_dur": 0, "idx": 191},
                  {"tick": 11760, "key": 0, "dur": 0, "isEnd": 0, "toTrack": 0, "volume": 0, "pan": 0, "attr": 0, "time": 109701, "time_dur": 0, "idx": 192},
                  {"tick": 12264, "key": 0, "dur": 48, "isEnd": 1, "toTrack": 7, "volume": 0, "pan": 0, "attr": 3, "time": 114402, "time_dur": 447, "idx": 201},
                  {"tick": 12480, "key": 0, "dur": 216, "isEnd": 1, "toTrack": 7, "volume": 0, "pan": 0, "attr": 3, "time": 116417, "time_dur": 2014, "idx": 206},
                  {"tick": 13152, "key": 0, "dur": 0, "isEnd": 0, "toTrack": 0, "volume": 0, "pan": 0, "attr": 0, "time": 122686, "time_dur": 0, "idx": 209},
                  {"tick": 13632, "key": 0, "dur": 0, "isEnd": 0, "toTrack": 0, "volume": 0, "pan": 0, "attr": 0, "time": 127164, "time_dur": 0, "idx": 211},
                  {"tick": 14448, "key": 0, "dur": 0, "isEnd": 0, "toTrack": 0, "volume": 0, "pan": 0, "attr": 0, "time": 134775, "time_dur": 0, "idx": 219},
                  {"tick": 14640, "key": 0, "dur": 0, "isEnd": 0, "toTrack": 0, "volume": 0, "pan": 0, "attr": 0, "time": 136566, "time_dur": 0, "idx": 223},
                  {"tick": 14832, "key": 0, "dur": 0, "isEnd": 0, "toTrack": 0, "volume": 0, "pan": 0, "attr": 0, "time": 138357, "time_dur": 0, "idx": 227},
                  {"tick": 15024, "key": 0, "dur": 0, "isEnd": 0, "toTrack": 0, "volume": 0, "pan": 0, "attr": 0, "time": 140148, "time_dur": 0, "idx": 231},
                  {"tick": 15168, "key": 0, "dur": 0, "isEnd": 0, "toTrack": 0, "volume": 0, "pan": 0, "attr": 0, "time": 141491, "time_dur": 0, "idx": 234},
                  {"tick": 15360, "key": 0, "dur": 0, "isEnd": 0, "toTrack": 0, "volume": 0, "pan": 0, "attr": 0, "time": 143282, "time_dur": 0, "idx": 238},
                  {"tick": 15936, "key": 0, "dur": 192, "isEnd": 1, "toTrack": 7, "volume": 0, "pan": 0, "attr": 3, "time": 148656, "time_dur": 1791, "idx": 245}
            ]
        },
        {
            "track": 63, 
            "note": [
                  {"tick": 16477, "key": 0, "dur": 0, "isEnd": 0, "toTrack": 0, "volume": 0, "pan": 0, "attr": 202, "time": 153704, "time_dur": 0, "idx": 0}
            ]
        }
    ]
}