{
    "signature": "BNDQ",
    "version": "1.3.0",
    "tempo": 140.000000,
    "duration": 12101,
    "durationtime": 108042,
    "samples": [

    ], 
    "tracks": [
        {
            "track": 3, 
            "note": [
                  {"tick": 576, "key": 0, "dur": 0, "isEnd": 0, "toTrack": 0, "volume": 0, "pan": 0, "attr": 0, "time": 5142, "time_dur": 0, "idx": 0},
                  {"tick": 624, "key": 0, "dur": 0, "isEnd": 0, "toTrack": 0, "volume": 0, "pan": 0, "attr": 0, "time": 5571, "time_dur": 0, "idx": 1},
                  {"tick": 672, "key": 0, "dur": 0, "isEnd": 0, "toTrack": 0, "volume": 0, "pan": 0, "attr": 0, "time": 6000, "time_dur": 0, "idx": 2},
                  {"tick": 720, "key": 0, "dur": 0, "isEnd": 0, "toTrack": 0, "volume": 0, "pan": 0, "attr": 0, "time": 6428, "time_dur": 0, "idx": 3},
                  {"tick": 768, "key": 0, "dur": 0, "isEnd": 0, "toTrack": 0, "volume": 0, "pan": 0, "attr": 0, "time": 6857, "time_dur": 0, "idx": 4},
                  {"tick": 960, "key": 0, "dur": 0, "isEnd": 0, "toTrack": 0, "volume": 0, "pan": 0, "attr": 0, "time": 8571, "time_dur": 0, "idx": 7},
                  {"tick": 1152, "key": 0, "dur": 0, "isEnd": 0, "toTrack": 0, "volume": 0, "pan": 0, "attr": 0, "time": 10285, "time_dur": 0, "idx": 10},
                  {"tick": 1536, "key": 0, "dur": 0, "isEnd": 0, "toTrack": 0, "volume": 0, "pan": 0, "attr": 0, "time": 13714, "time_dur": 0, "idx": 16},
                  {"tick": 1728, "key": 0, "dur": 0, "isEnd": 0, "toTrack": 0, "volume": 0, "pan": 0, "attr": 0, "time": 15428, "time_dur": 0, "idx": 19},
                  {"tick": 1920, "key": 0, "dur": 0, "isEnd": 0, "toTrack": 0, "volume": 0, "pan": 0, "attr": 0, "time": 17142, "time_dur": 0, "idx": 22},
                  {"tick": 2304, "key": 0, "dur": 0, "isEnd": 0, "toTrack": 0, "volume": 0, "pan": 0, "attr": 0, "time": 20571, "time_dur": 0, "idx": 28},
                  {"tick": 2352, "key": 0, "dur": 0, "isEnd": 0, "toTrack": 0, "volume": 0, "pan": 0, "attr": 0, "time": 21000, "time_dur": 0, "idx": 29},
                  {"tick": 3072, "key": 0, "dur": 0, "isEnd": 0, "toTrack": 0, "volume": 0, "pan": 0, "attr": 0, "time": 27428, "time_dur": 0, "idx": 41},
                  {"tick": 3120, "key": 0, "dur": 0, "isEnd": 0, "toTrack": 0, "volume": 0, "pan": 0, "attr": 0, "time": 27857, "time_dur": 0, "idx": 42},
                  {"tick": 3648, "key": 0, "dur": 144, "isEnd": 1, "toTrack": 3, "volume": 0, "pan": 0, "attr": 3, "time": 32571, "time_dur": 1286, "idx": 50},
                  {"tick": 4056, "key": 0, "dur": 0, "isEnd": 0, "toTrack": 0, "volume": 0, "pan": 0, "attr": 0, "time": 36214, "time_dur": 0, "idx": 54},
                  {"tick": 4272, "key": 0, "dur": 0, "isEnd": 0, "toTrack": 0, "volume": 0, "pan": 0, "attr": 0, "time": 38142, "time_dur": 0, "idx": 58},
                  {"tick": 4320, "key": 0, "dur": 0, "isEnd": 0, "toTrack": 0, "volume": 0, "pan": 0, "attr": 0, "time": 38571, "time_dur": 0, "idx": 59},
                  {"tick": 4848, "key": 0, "dur": 0, "isEnd": 0, "toTrack": 0, "volume": 0, "pan": 0, "attr": 0, "time": 43285, "time_dur": 0, "idx": 65},
                  {"tick": 5040, "key": 0, "dur": 0, "isEnd": 0, "toTrack": 0, "volume": 0, "pan": 0, "attr": 0, "time": 45000, "time_dur": 0, "idx": 69},
                  {"tick": 5616, "key": 0, "dur": 0, "isEnd": 0, "toTrack": 0, "volume": 0, "pan": 0, "attr": 0, "time": 50142, "time_dur": 0, "idx": 77},
                  {"tick": 6408, "key": 0, "dur": 0, "isEnd": 0, "toTrack": 0, "volume": 0, "pan": 0, "attr": 0, "time": 57214, "time_dur": 0, "idx": 89},
                  {"tick": 6912, "key": 0, "dur": 0, "isEnd": 0, "toTrack": 0, "volume": 0, "pan": 0, "attr": 0, "time": 61714, "time_dur": 0, "idx": 94},
                  {"tick": 7008, "key": 0, "dur": 0, "isEnd": 0, "toTrack": 0, "volume": 0, "pan": 0, "attr": 0, "time": 62571, "time_dur": 0, "idx": 96},
                  {"tick": 7104, "key": 0, "dur": 0, "isEnd": 0, "toTrack": 0, "volume": 0, "pan": 0, "attr": 0, "time": 63428, "time_dur": 0, "idx": 98},
                  {"tick": 7200, "key": 0, "dur": 0, "isEnd": 0, "toTrack": 0, "volume": 0, "pan": 0, "attr": 0, "time": 64285, "time_dur": 0, "idx": 100},
                  {"tick": 8160, "key": 0, "dur": 0, "isEnd": 0, "toTrack": 0, "volume": 0, "pan": 0, "attr": 0, "time": 72857, "time_dur": 0, "idx": 120},
                  {"tick": 8208, "key": 0, "dur": 0, "isEnd": 0, "toTrack": 0, "volume": 0, "pan": 0, "attr": 0, "time": 73285, "time_dur": 0, "idx": 121},
                  {"tick": 8448, "key": 0, "dur": 0, "isEnd": 0, "toTrack": 0, "volume": 0, "pan": 0, "attr": 0, "time": 75428, "time_dur": 0, "idx": 125},
                  {"tick": 8544, "key": 0, "dur": 0, "isEnd": 0, "toTrack": 0, "volume": 0, "pan": 0, "attr": 0, "time": 76285, "time_dur": 0, "idx": 127},
                  {"tick": 8640, "key": 0, "dur": 0, "isEnd": 0, "toTrack": 0, "volume": 0, "pan": 0, "attr": 0, "time": 77142, "time_dur": 0, "idx": 129},
                  {"tick": 8736, "key": 0, "dur": 0, "isEnd": 0, "toTrack": 0, "volume": 0, "pan": 0, "attr": 0, "time": 77999, "time_dur": 0, "idx": 131},
                  {"tick": 9216, "key": 0, "dur": 0, "isEnd": 0, "toTrack": 0, "volume": 0, "pan": 0, "attr": 0, "time": 82285, "time_dur": 0, "idx": 141},
                  {"tick": 9408, "key": 0, "dur": 0, "isEnd": 0, "toTrack": 0, "volume": 0, "pan": 0, "attr": 0, "time": 84000, "time_dur": 0, "idx": 145},
                  {"tick": 9792, "key": 0, "dur": 0, "isEnd": 0, "toTrack": 0, "volume": 0, "pan": 0, "attr": 0, "time": 87428, "time_dur": 0, "idx": 153},
                  {"tick": 10608, "key": 0, "dur": 0, "isEnd": 0, "toTrack": 0, "volume": 0, "pan": 0, "attr": 0, "time": 94714, "time_dur": 0, "idx": 170},
                  {"tick": 10704, "key": 0, "dur": 0, "isEnd": 0, "toTrack": 0, "volume": 0, "pan": 0, "attr": 0, "time": 95571, "time_dur": 0, "idx": 172}
            ]
        },
        {
            "track": 4, 
            "note": [
                  {"tick": 1440, "key": 0, "dur": 0, "isEnd": 0, "toTrack": 0, "volume": 0, "pan": 0, "attr": 0, "time": 12857, "time_dur": 0, "idx": 14},
                  {"tick": 2208, "key": 0, "dur": 0, "isEnd": 0, "toTrack": 0, "volume": 0, "pan": 0, "attr": 0, "time": 19714, "time_dur": 0, "idx": 26},
                  {"tick": 2880, "key": 0, "dur": 0, "isEnd": 0, "toTrack": 0, "volume": 0, "pan": 0, "attr": 0, "time": 25714, "time_dur": 0, "idx": 37},
                  {"tick": 2928, "key": 0, "dur": 0, "isEnd": 0, "toTrack": 0, "volume": 0, "pan": 0, "attr": 0, "time": 26142, "time_dur": 0, "idx": 38},
                  {"tick": 2976, "key": 0, "dur": 0, "isEnd": 0, "toTrack": 0, "volume": 0, "pan": 0, "attr": 0, "time": 26571, "time_dur": 0, "idx": 39},
                  {"tick": 3024, "key": 0, "dur": 0, "isEnd": 0, "toTrack": 0, "volume": 0, "pan": 0, "attr": 0, "time": 27000, "time_dur": 0, "idx": 40},
                  {"tick": 3936, "key": 0, "dur": 0, "isEnd": 0, "toTrack": 0, "volume": 0, "pan": 0, "attr": 0, "time": 35142, "time_dur": 0, "idx": 52},
                  {"tick": 4776, "key": 0, "dur": 0, "isEnd": 0, "toTrack": 0, "volume": 0, "pan": 0, "attr": 0, "time": 42642, "time_dur": 0, "idx": 64},
                  {"tick": 5088, "key": 0, "dur": 0, "isEnd": 0, "toTrack": 0, "volume": 0, "pan": 0, "attr": 0, "time": 45428, "time_dur": 0, "idx": 70},
                  {"tick": 5376, "key": 0, "dur": 0, "isEnd": 1, "toTrack": 3, "volume": 0, "pan": 0, "attr": 3, "time": 48000, "time_dur": -1, "idx": 73},
                  {"tick": 5496, "key": 0, "dur": 0, "isEnd": 0, "toTrack": 0, "volume": 0, "pan": 0, "attr": 0, "time": 49071, "time_dur": 0, "idx": 74},
                  {"tick": 5832, "key": 0, "dur": 0, "isEnd": 0, "toTrack": 0, "volume": 0, "pan": 0, "attr": 0, "time": 52071, "time_dur": 0, "idx": 81},
                  {"tick": 6144, "key": 0, "dur": 0, "isEnd": 1, "toTrack": 3, "volume": 0, "pan": 0, "attr": 3, "time": 54857, "time_dur": -1, "idx": 84},
                  {"tick": 6312, "key": 0, "dur": 0, "isEnd": 0, "toTrack": 0, "volume": 0, "pan": 0, "attr": 0, "time": 56356, "time_dur": 0, "idx": 87},
                  {"tick": 6576, "key": 0, "dur": 0, "isEnd": 0, "toTrack": 0, "volume": 0, "pan": 0, "attr": 0, "time": 58714, "time_dur": 0, "idx": 92},
                  {"tick": 6612, "key": 0, "dur": 108, "isEnd": 1, "toTrack": 4, "volume": 0, "pan": 0, "attr": 3, "time": 59035, "time_dur": 965, "idx": 93},
                  {"tick": 7296, "key": 0, "dur": 0, "isEnd": 0, "toTrack": 0, "volume": 0, "pan": 0, "attr": 0, "time": 65142, "time_dur": 0, "idx": 102},
                  {"tick": 7392, "key": 0, "dur": 0, "isEnd": 0, "toTrack": 0, "volume": 0, "pan": 0, "attr": 0, "time": 66000, "time_dur": 0, "idx": 104},
                  {"tick": 7488, "key": 0, "dur": 0, "isEnd": 0, "toTrack": 0, "volume": 0, "pan": 0, "attr": 0, "time": 66857, "time_dur": 0, "idx": 106},
                  {"tick": 7584, "key": 0, "dur": 0, "isEnd": 0, "toTrack": 0, "volume": 0, "pan": 0, "attr": 0, "time": 67714, "time_dur": 0, "idx": 108},
                  {"tick": 8064, "key": 0, "dur": 0, "isEnd": 0, "toTrack": 0, "volume": 0, "pan": 0, "attr": 0, "time": 72000, "time_dur": 0, "idx": 118},
                  {"tick": 8832, "key": 0, "dur": 0, "isEnd": 0, "toTrack": 0, "volume": 0, "pan": 0, "attr": 0, "time": 78857, "time_dur": 0, "idx": 133},
                  {"tick": 8928, "key": 0, "dur": 0, "isEnd": 0, "toTrack": 0, "volume": 0, "pan": 0, "attr": 0, "time": 79714, "time_dur": 0, "idx": 135},
                  {"tick": 9024, "key": 0, "dur": 0, "isEnd": 0, "toTrack": 0, "volume": 0, "pan": 0, "attr": 0, "time": 80571, "time_dur": 0, "idx": 137},
                  {"tick": 9120, "key": 0, "dur": 0, "isEnd": 0, "toTrack": 0, "volume": 0, "pan": 0, "attr": 0, "time": 81428, "time_dur": 0, "idx": 139},
                  {"tick": 9312, "key": 0, "dur": 0, "isEnd": 0, "toTrack": 0, "volume": 0, "pan": 0, "attr": 0, "time": 83142, "time_dur": 0, "idx": 143},
                  {"tick": 9504, "key": 0, "dur": 0, "isEnd": 0, "toTrack": 0, "volume": 0, "pan": 0, "attr": 0, "time": 84857, "time_dur": 0, "idx": 147},
                  {"tick": 9696, "key": 0, "dur": 0, "isEnd": 0, "toTrack": 0, "volume": 0, "pan": 0, "attr": 0, "time": 86571, "time_dur": 0, "idx": 151},
                  {"tick": 9864, "key": 0, "dur": 72, "isEnd": 1, "toTrack": 4, "volume": 0, "pan": 0, "attr": 3, "time": 88071, "time_dur": 643, "idx": 155},
                  {"tick": 10104, "key": 0, "dur": 0, "isEnd": 0, "toTrack": 0, "volume": 0, "pan": 0, "attr": 0, "time": 90214, "time_dur": 0, "idx": 158},
                  {"tick": 10344, "key": 0, "dur": 0, "isEnd": 0, "toTrack": 0, "volume": 0, "pan": 0, "attr": 0, "time": 92356, "time_dur": 0, "idx": 163},
                  {"tick": 10536, "key": 0, "dur": 0, "isEnd": 0, "toTrack": 0, "volume": 0, "pan": 0, "attr": 0, "time": 94071, "time_dur": 0, "idx": 168},
                  {"tick": 10872, "key": 0, "dur": 0, "isEnd": 0, "toTrack": 0, "volume": 0, "pan": 0, "attr": 0, "time": 97071, "time_dur": 0, "idx": 175},
                  {"tick": 11112, "key": 0, "dur": 0, "isEnd": 0, "toTrack": 0, "volume": 0, "pan": 0, "attr": 0, "time": 99214, "time_dur": 0, "idx": 180},
                  {"tick": 11328, "key": 0, "dur": 144, "isEnd": 1, "toTrack": 4, "volume": 0, "pan": 0, "attr": 3, "time": 101142, "time_dur": 1286, "idx": 186}
            ]
        },
        {
            "track": 5, 
            "note": [
                  {"tick": 912, "key": 0, "dur": 0, "isEnd": 0, "toTrack": 0, "volume": 0, "pan": 0, "attr": 0, "time": 8142, "time_dur": 0, "idx": 6},
                  {"tick": 1104, "key": 0, "dur": 0, "isEnd": 0, "toTrack": 0, "volume": 0, "pan": 0, "attr": 0, "time": 9856, "time_dur": 0, "idx": 9},
                  {"tick": 1296, "key": 0, "dur": 0, "isEnd": 0, "toTrack": 0, "volume": 0, "pan": 0, "attr": 0, "time": 11570, "time_dur": 0, "idx": 12},
                  {"tick": 1680, "key": 0, "dur": 0, "isEnd": 0, "toTrack": 0, "volume": 0, "pan": 0, "attr": 0, "time": 14999, "time_dur": 0, "idx": 18},
                  {"tick": 1872, "key": 0, "dur": 0, "isEnd": 0, "toTrack": 0, "volume": 0, "pan": 0, "attr": 0, "time": 16713, "time_dur": 0, "idx": 21},
                  {"tick": 2064, "key": 0, "dur": 0, "isEnd": 0, "toTrack": 0, "volume": 0, "pan": 0, "attr": 0, "time": 18428, "time_dur": 0, "idx": 24},
                  {"tick": 2688, "key": 0, "dur": 0, "isEnd": 0, "toTrack": 0, "volume": 0, "pan": 0, "attr": 0, "time": 24000, "time_dur": 0, "idx": 34},
                  {"tick": 2736, "key": 0, "dur": 0, "isEnd": 0, "toTrack": 0, "volume": 0, "pan": 0, "attr": 0, "time": 24428, "time_dur": 0, "idx": 35},
                  {"tick": 2808, "key": 0, "dur": 0, "isEnd": 0, "toTrack": 0, "volume": 0, "pan": 0, "attr": 0, "time": 25071, "time_dur": 0, "idx": 36},
                  {"tick": 3456, "key": 0, "dur": 0, "isEnd": 0, "toTrack": 0, "volume": 0, "pan": 0, "attr": 0, "time": 30857, "time_dur": 0, "idx": 47},
                  {"tick": 3504, "key": 0, "dur": 0, "isEnd": 0, "toTrack": 0, "volume": 0, "pan": 0, "attr": 0, "time": 31285, "time_dur": 0, "idx": 48},
                  {"tick": 3576, "key": 0, "dur": 0, "isEnd": 0, "toTrack": 0, "volume": 0, "pan": 0, "attr": 0, "time": 31928, "time_dur": 0, "idx": 49},
                  {"tick": 4104, "key": 0, "dur": 0, "isEnd": 0, "toTrack": 0, "volume": 0, "pan": 0, "attr": 0, "time": 36642, "time_dur": 0, "idx": 55},
                  {"tick": 4392, "key": 0, "dur": 96, "isEnd": 1, "toTrack": 5, "volume": 0, "pan": 0, "attr": 3, "time": 39214, "time_dur": 857, "idx": 61},
                  {"tick": 4920, "key": 0, "dur": 24, "isEnd": 1, "toTrack": 5, "volume": 0, "pan": 0, "attr": 3, "time": 43928, "time_dur": 214, "idx": 67},
                  {"tick": 5688, "key": 0, "dur": 0, "isEnd": 0, "toTrack": 0, "volume": 0, "pan": 0, "attr": 0, "time": 50785, "time_dur": 0, "idx": 79},
                  {"tick": 6264, "key": 0, "dur": 0, "isEnd": 0, "toTrack": 0, "volume": 0, "pan": 0, "attr": 0, "time": 55928, "time_dur": 0, "idx": 85},
                  {"tick": 7680, "key": 0, "dur": 0, "isEnd": 0, "toTrack": 0, "volume": 0, "pan": 0, "attr": 0, "time": 68571, "time_dur": 0, "idx": 110},
                  {"tick": 7776, "key": 0, "dur": 0, "isEnd": 0, "toTrack": 0, "volume": 0, "pan": 0, "attr": 0, "time": 69428, "time_dur": 0, "idx": 112},
                  {"tick": 7872, "key": 0, "dur": 0, "isEnd": 0, "toTrack": 0, "volume": 0, "pan": 0, "attr": 0, "time": 70285, "time_dur": 0, "idx": 114},
                  {"tick": 7968, "key": 0, "dur": 0, "isEnd": 0, "toTrack": 0, "volume": 0, "pan": 0, "attr": 0, "time": 71142, "time_dur": 0, "idx": 116},
                  {"tick": 8304, "key": 0, "dur": 0, "isEnd": 0, "toTrack": 0, "volume": 0, "pan": 0, "attr": 0, "time": 74142, "time_dur": 0, "idx": 123},
                  {"tick": 8328, "key": 0, "dur": 72, "isEnd": 1, "toTrack": 5, "volume": 0, "pan": 0, "attr": 3, "time": 74356, "time_dur": 644, "idx": 124},
                  {"tick": 9600, "key": 0, "dur": 0, "isEnd": 0, "toTrack": 0, "volume": 0, "pan": 0, "attr": 0, "time": 85714, "time_dur": 0, "idx": 149},
                  {"tick": 10176, "key": 0, "dur": 24, "isEnd": 1, "toTrack": 5, "volume": 0, "pan": 0, "attr": 3, "time": 90857, "time_dur": 214, "idx": 160},
                  {"tick": 10224, "key": 0, "dur": 0, "isEnd": 0, "toTrack": 0, "volume": 0, "pan": 0, "attr": 0, "time": 91285, "time_dur": 0, "idx": 161},
                  {"tick": 10944, "key": 0, "dur": 24, "isEnd": 1, "toTrack": 5, "volume": 0, "pan": 0, "attr": 3, "time": 97714, "time_dur": 214, "idx": 177},
                  {"tick": 10992, "key": 0, "dur": 0, "isEnd": 0, "toTrack": 0, "volume": 0, "pan": 0, "attr": 0, "time": 98142, "time_dur": 0, "idx": 178}
            ]
        },
        {
            "track": 6, 
            "note": [
                  {"tick": 1488, "key": 0, "dur": 0, "isEnd": 0, "toTrack": 0, "volume": 0, "pan": 0, "attr": 0, "time": 13285, "time_dur": 0, "idx": 15},
                  {"tick": 2256, "key": 0, "dur": 0, "isEnd": 0, "toTrack": 0, "volume": 0, "pan": 0, "attr": 0, "time": 20142, "time_dur": 0, "idx": 27},
                  {"tick": 2424, "key": 0, "dur": 0, "isEnd": 0, "toTrack": 0, "volume": 0, "pan": 0, "attr": 0, "time": 21642, "time_dur": 0, "idx": 30},
                  {"tick": 2496, "key": 0, "dur": 0, "isEnd": 0, "toTrack": 0, "volume": 0, "pan": 0, "attr": 0, "time": 22285, "time_dur": 0, "idx": 31},
                  {"tick": 2544, "key": 0, "dur": 0, "isEnd": 0, "toTrack": 0, "volume": 0, "pan": 0, "attr": 0, "time": 22714, "time_dur": 0, "idx": 32},
                  {"tick": 3192, "key": 0, "dur": 0, "isEnd": 0, "toTrack": 0, "volume": 0, "pan": 0, "attr": 0, "time": 28499, "time_dur": 0, "idx": 43},
                  {"tick": 3264, "key": 0, "dur": 0, "isEnd": 0, "toTrack": 0, "volume": 0, "pan": 0, "attr": 0, "time": 29142, "time_dur": 0, "idx": 44},
                  {"tick": 3312, "key": 0, "dur": 0, "isEnd": 0, "toTrack": 0, "volume": 0, "pan": 0, "attr": 0, "time": 29571, "time_dur": 0, "idx": 45},
                  {"tick": 4008, "key": 0, "dur": 0, "isEnd": 0, "toTrack": 0, "volume": 0, "pan": 0, "attr": 0, "time": 35785, "time_dur": 0, "idx": 53},
                  {"tick": 4224, "key": 0, "dur": 0, "isEnd": 0, "toTrack": 0, "volume": 0, "pan": 0, "attr": 0, "time": 37714, "time_dur": 0, "idx": 57},
                  {"tick": 4872, "key": 0, "dur": 0, "isEnd": 0, "toTrack": 0, "volume": 0, "pan": 0, "attr": 0, "time": 43499, "time_dur": 0, "idx": 66},
                  {"tick": 5160, "key": 0, "dur": 120, "isEnd": 1, "toTrack": 6, "volume": 0, "pan": 0, "attr": 3, "time": 46071, "time_dur": 1071, "idx": 72},
                  {"tick": 5568, "key": 0, "dur": 0, "isEnd": 0, "toTrack": 0, "volume": 0, "pan": 0, "attr": 0, "time": 49714, "time_dur": 0, "idx": 76},
                  {"tick": 5880, "key": 0, "dur": 0, "isEnd": 0, "toTrack": 0, "volume": 0, "pan": 0, "attr": 0, "time": 52499, "time_dur": 0, "idx": 82},
                  {"tick": 5928, "key": 0, "dur": 48, "isEnd": 1, "toTrack": 6, "volume": 0, "pan": 0, "attr": 3, "time": 52928, "time_dur": 428, "idx": 83},
                  {"tick": 6384, "key": 0, "dur": 0, "isEnd": 0, "toTrack": 0, "volume": 0, "pan": 0, "attr": 0, "time": 57000, "time_dur": 0, "idx": 88},
                  {"tick": 6528, "key": 0, "dur": 0, "isEnd": 0, "toTrack": 0, "volume": 0, "pan": 0, "attr": 0, "time": 58285, "time_dur": 0, "idx": 91},
                  {"tick": 6960, "key": 0, "dur": 0, "isEnd": 0, "toTrack": 0, "volume": 0, "pan": 0, "attr": 0, "time": 62142, "time_dur": 0, "idx": 95},
                  {"tick": 7056, "key": 0, "dur": 0, "isEnd": 0, "toTrack": 0, "volume": 0, "pan": 0, "attr": 0, "time": 63000, "time_dur": 0, "idx": 97},
                  {"tick": 7152, "key": 0, "dur": 0, "isEnd": 0, "toTrack": 0, "volume": 0, "pan": 0, "attr": 0, "time": 63856, "time_dur": 0, "idx": 99},
                  {"tick": 7248, "key": 0, "dur": 0, "isEnd": 0, "toTrack": 0, "volume": 0, "pan": 0, "attr": 0, "time": 64714, "time_dur": 0, "idx": 101},
                  {"tick": 9264, "key": 0, "dur": 0, "isEnd": 0, "toTrack": 0, "volume": 0, "pan": 0, "attr": 0, "time": 82714, "time_dur": 0, "idx": 142},
                  {"tick": 9456, "key": 0, "dur": 0, "isEnd": 0, "toTrack": 0, "volume": 0, "pan": 0, "attr": 0, "time": 84428, "time_dur": 0, "idx": 146},
                  {"tick": 9840, "key": 0, "dur": 0, "isEnd": 0, "toTrack": 0, "volume": 0, "pan": 0, "attr": 0, "time": 87857, "time_dur": 0, "idx": 154},
                  {"tick": 9984, "key": 0, "dur": 24, "isEnd": 1, "toTrack": 6, "volume": 0, "pan": 0, "attr": 3, "time": 89142, "time_dur": 214, "idx": 156},
                  {"tick": 10032, "key": 0, "dur": 0, "isEnd": 0, "toTrack": 0, "volume": 0, "pan": 0, "attr": 0, "time": 89571, "time_dur": 0, "idx": 157},
                  {"tick": 10488, "key": 0, "dur": 0, "isEnd": 0, "toTrack": 0, "volume": 0, "pan": 0, "attr": 0, "time": 93642, "time_dur": 0, "idx": 167},
                  {"tick": 10752, "key": 0, "dur": 24, "isEnd": 1, "toTrack": 6, "volume": 0, "pan": 0, "attr": 3, "time": 96000, "time_dur": 214, "idx": 173},
                  {"tick": 10800, "key": 0, "dur": 0, "isEnd": 0, "toTrack": 0, "volume": 0, "pan": 0, "attr": 0, "time": 96428, "time_dur": 0, "idx": 174},
                  {"tick": 11256, "key": 0, "dur": 0, "isEnd": 0, "toTrack": 0, "volume": 0, "pan": 0, "attr": 0, "time": 100499, "time_dur": 0, "idx": 184}
            ]
        },
        {
            "track": 7, 
            "note": [
                  {"tick": 840, "key": 0, "dur": 0, "isEnd": 0, "toTrack": 0, "volume": 0, "pan": 0, "attr": 0, "time": 7499, "time_dur": 0, "idx": 5},
                  {"tick": 1032, "key": 0, "dur": 0, "isEnd": 0, "toTrack": 0, "volume": 0, "pan": 0, "attr": 0, "time": 9214, "time_dur": 0, "idx": 8},
                  {"tick": 1224, "key": 0, "dur": 0, "isEnd": 0, "toTrack": 0, "volume": 0, "pan": 0, "attr": 0, "time": 10928, "time_dur": 0, "idx": 11},
                  {"tick": 1608, "key": 0, "dur": 0, "isEnd": 0, "toTrack": 0, "volume": 0, "pan": 0, "attr": 0, "time": 14356, "time_dur": 0, "idx": 17},
                  {"tick": 1800, "key": 0, "dur": 0, "isEnd": 0, "toTrack": 0, "volume": 0, "pan": 0, "attr": 0, "time": 16071, "time_dur": 0, "idx": 20},
                  {"tick": 1992, "key": 0, "dur": 0, "isEnd": 0, "toTrack": 0, "volume": 0, "pan": 0, "attr": 0, "time": 17785, "time_dur": 0, "idx": 23},
                  {"tick": 3888, "key": 0, "dur": 0, "isEnd": 0, "toTrack": 0, "volume": 0, "pan": 0, "attr": 0, "time": 34714, "time_dur": 0, "idx": 51},
                  {"tick": 4344, "key": 0, "dur": 0, "isEnd": 0, "toTrack": 0, "volume": 0, "pan": 0, "attr": 0, "time": 38785, "time_dur": 0, "idx": 60},
                  {"tick": 4656, "key": 0, "dur": 0, "isEnd": 0, "toTrack": 0, "volume": 0, "pan": 0, "attr": 0, "time": 41571, "time_dur": 0, "idx": 62},
                  {"tick": 4704, "key": 0, "dur": 0, "isEnd": 0, "toTrack": 0, "volume": 0, "pan": 0, "attr": 0, "time": 42000, "time_dur": 0, "idx": 63},
                  {"tick": 5112, "key": 0, "dur": 0, "isEnd": 0, "toTrack": 0, "volume": 0, "pan": 0, "attr": 0, "time": 45642, "time_dur": 0, "idx": 71},
                  {"tick": 5520, "key": 0, "dur": 0, "isEnd": 0, "toTrack": 0, "volume": 0, "pan": 0, "attr": 0, "time": 49285, "time_dur": 0, "idx": 75},
                  {"tick": 5760, "key": 0, "dur": 0, "isEnd": 0, "toTrack": 0, "volume": 0, "pan": 0, "attr": 0, "time": 51428, "time_dur": 0, "idx": 80},
                  {"tick": 6288, "key": 0, "dur": 0, "isEnd": 0, "toTrack": 0, "volume": 0, "pan": 0, "attr": 0, "time": 56142, "time_dur": 0, "idx": 86},
                  {"tick": 7344, "key": 0, "dur": 0, "isEnd": 0, "toTrack": 0, "volume": 0, "pan": 0, "attr": 0, "time": 65571, "time_dur": 0, "idx": 103},
                  {"tick": 7440, "key": 0, "dur": 0, "isEnd": 0, "toTrack": 0, "volume": 0, "pan": 0, "attr": 0, "time": 66428, "time_dur": 0, "idx": 105},
                  {"tick": 7536, "key": 0, "dur": 0, "isEnd": 0, "toTrack": 0, "volume": 0, "pan": 0, "attr": 0, "time": 67285, "time_dur": 0, "idx": 107},
                  {"tick": 7632, "key": 0, "dur": 0, "isEnd": 0, "toTrack": 0, "volume": 0, "pan": 0, "attr": 0, "time": 68142, "time_dur": 0, "idx": 109},
                  {"tick": 8112, "key": 0, "dur": 0, "isEnd": 0, "toTrack": 0, "volume": 0, "pan": 0, "attr": 0, "time": 72428, "time_dur": 0, "idx": 119},
                  {"tick": 8880, "key": 0, "dur": 0, "isEnd": 0, "toTrack": 0, "volume": 0, "pan": 0, "attr": 0, "time": 79285, "time_dur": 0, "idx": 134},
                  {"tick": 8976, "key": 0, "dur": 0, "isEnd": 0, "toTrack": 0, "volume": 0, "pan": 0, "attr": 0, "time": 80142, "time_dur": 0, "idx": 136},
                  {"tick": 9072, "key": 0, "dur": 0, "isEnd": 0, "toTrack": 0, "volume": 0, "pan": 0, "attr": 0, "time": 80999, "time_dur": 0, "idx": 138},
                  {"tick": 9168, "key": 0, "dur": 0, "isEnd": 0, "toTrack": 0, "volume": 0, "pan": 0, "attr": 0, "time": 81856, "time_dur": 0, "idx": 140},
                  {"tick": 9360, "key": 0, "dur": 0, "isEnd": 0, "toTrack": 0, "volume": 0, "pan": 0, "attr": 0, "time": 83571, "time_dur": 0, "idx": 144},
                  {"tick": 9552, "key": 0, "dur": 0, "isEnd": 0, "toTrack": 0, "volume": 0, "pan": 0, "attr": 0, "time": 85285, "time_dur": 0, "idx": 148},
                  {"tick": 9744, "key": 0, "dur": 0, "isEnd": 0, "toTrack": 0, "volume": 0, "pan": 0, "attr": 0, "time": 87000, "time_dur": 0, "idx": 152},
                  {"tick": 10152, "key": 0, "dur": 0, "isEnd": 0, "toTrack": 0, "volume": 0, "pan": 0, "attr": 0, "time": 90642, "time_dur": 0, "idx": 159},
                  {"tick": 10368, "key": 0, "dur": 24, "isEnd": 1, "toTrack": 7, "volume": 0, "pan": 0, "attr": 3, "time": 92571, "time_dur": 214, "idx": 164},
                  {"tick": 10416, "key": 0, "dur": 0, "isEnd": 0, "toTrack": 0, "volume": 0, "pan": 0, "attr": 0, "time": 93000, "time_dur": 0, "idx": 165},
                  {"tick": 10440, "key": 0, "dur": 0, "isEnd": 0, "toTrack": 0, "volume": 0, "pan": 0, "attr": 0, "time": 93214, "time_dur": 0, "idx": 166},
                  {"tick": 10560, "key": 0, "dur": 0, "isEnd": 0, "toTrack": 0, "volume": 0, "pan": 0, "attr": 0, "time": 94285, "time_dur": 0, "idx": 169},
                  {"tick": 10920, "key": 0, "dur": 0, "isEnd": 0, "toTrack": 0, "volume": 0, "pan": 0, "attr": 0, "time": 97499, "time_dur": 0, "idx": 176},
                  {"tick": 11136, "key": 0, "dur": 24, "isEnd": 1, "toTrack": 7, "volume": 0, "pan": 0, "attr": 3, "time": 99428, "time_dur": 214, "idx": 181},
                  {"tick": 11184, "key": 0, "dur": 0, "isEnd": 0, "toTrack": 0, "volume": 0, "pan": 0, "attr": 0, "time": 99857, "time_dur": 0, "idx": 182},
                  {"tick": 11208, "key": 0, "dur": 0, "isEnd": 0, "toTrack": 0, "volume": 0, "pan": 0, "attr": 0, "time": 100071, "time_dur": 0, "idx": 183},
                  {"tick": 11304, "key": 0, "dur": 0, "isEnd": 0, "toTrack": 0, "volume": 0, "pan": 0, "attr": 0, "time": 100928, "time_dur": 0, "idx": 185},
                  {"tick": 11520, "key": 0, "dur": 0, "isEnd": 1, "toTrack": 8, "volume": 0, "pan": 0, "attr": 3, "time": 102857, "time_dur": 1, "idx": 187}
            ]
        },
        {
            "track": 8, 
            "note": [
                  {"tick": 1344, "key": 0, "dur": 0, "isEnd": 0, "toTrack": 0, "volume": 0, "pan": 0, "attr": 0, "time": 12000, "time_dur": 0, "idx": 13},
                  {"tick": 2112, "key": 0, "dur": 0, "isEnd": 0, "toTrack": 0, "volume": 0, "pan": 0, "attr": 0, "time": 18857, "time_dur": 0, "idx": 25},
                  {"tick": 2616, "key": 0, "dur": 0, "isEnd": 0, "toTrack": 0, "volume": 0, "pan": 0, "attr": 0, "time": 23356, "time_dur": 0, "idx": 33},
                  {"tick": 3384, "key": 0, "dur": 0, "isEnd": 0, "toTrack": 0, "volume": 0, "pan": 0, "attr": 0, "time": 30214, "time_dur": 0, "idx": 46},
                  {"tick": 4152, "key": 0, "dur": 24, "isEnd": 1, "toTrack": 8, "volume": 0, "pan": 0, "attr": 3, "time": 37071, "time_dur": 214, "idx": 56},
                  {"tick": 4992, "key": 0, "dur": 0, "isEnd": 0, "toTrack": 0, "volume": 0, "pan": 0, "attr": 0, "time": 44571, "time_dur": 0, "idx": 68},
                  {"tick": 5640, "key": 0, "dur": 0, "isEnd": 0, "toTrack": 0, "volume": 0, "pan": 0, "attr": 0, "time": 50356, "time_dur": 0, "idx": 78},
                  {"tick": 6480, "key": 0, "dur": 0, "isEnd": 0, "toTrack": 0, "volume": 0, "pan": 0, "attr": 0, "time": 57857, "time_dur": 0, "idx": 90},
                  {"tick": 7728, "key": 0, "dur": 0, "isEnd": 0, "toTrack": 0, "volume": 0, "pan": 0, "attr": 0, "time": 69000, "time_dur": 0, "idx": 111},
                  {"tick": 7824, "key": 0, "dur": 0, "isEnd": 0, "toTrack": 0, "volume": 0, "pan": 0, "attr": 0, "time": 69857, "time_dur": 0, "idx": 113},
                  {"tick": 7920, "key": 0, "dur": 0, "isEnd": 0, "toTrack": 0, "volume": 0, "pan": 0, "attr": 0, "time": 70714, "time_dur": 0, "idx": 115},
                  {"tick": 8016, "key": 0, "dur": 0, "isEnd": 0, "toTrack": 0, "volume": 0, "pan": 0, "attr": 0, "time": 71571, "time_dur": 0, "idx": 117},
                  {"tick": 8256, "key": 0, "dur": 0, "isEnd": 0, "toTrack": 0, "volume": 0, "pan": 0, "attr": 0, "time": 73714, "time_dur": 0, "idx": 122},
                  {"tick": 8496, "key": 0, "dur": 0, "isEnd": 0, "toTrack": 0, "volume": 0, "pan": 0, "attr": 0, "time": 75857, "time_dur": 0, "idx": 126},
                  {"tick": 8592, "key": 0, "dur": 0, "isEnd": 0, "toTrack": 0, "volume": 0, "pan": 0, "attr": 0, "time": 76714, "time_dur": 0, "idx": 128},
                  {"tick": 8688, "key": 0, "dur": 0, "isEnd": 0, "toTrack": 0, "volume": 0, "pan": 0, "attr": 0, "time": 77571, "time_dur": 0, "idx": 130},
                  {"tick": 8784, "key": 0, "dur": 0, "isEnd": 0, "toTrack": 0, "volume": 0, "pan": 0, "attr": 0, "time": 78428, "time_dur": 0, "idx": 132},
                  {"tick": 9648, "key": 0, "dur": 0, "isEnd": 0, "toTrack": 0, "volume": 0, "pan": 0, "attr": 0, "time": 86142, "time_dur": 0, "idx": 150},
                  {"tick": 10296, "key": 0, "dur": 0, "isEnd": 0, "toTrack": 0, "volume": 0, "pan": 0, "attr": 0, "time": 91928, "time_dur": 0, "idx": 162},
                  {"tick": 10656, "key": 0, "dur": 0, "isEnd": 0, "toTrack": 0, "volume": 0, "pan": 0, "attr": 0, "time": 95142, "time_dur": 0, "idx": 171},
                  {"tick": 11064, "key": 0, "dur": 0, "isEnd": 0, "toTrack": 0, "volume": 0, "pan": 0, "attr": 0, "time": 98785, "time_dur": 0, "idx": 179}
            ]
        },
        {
            "track": 63, 
            "note": [
                  {"tick": 12101, "key": 0, "dur": 0, "isEnd": 0, "toTrack": 0, "volume": 0, "pan": 0, "attr": 202, "time": 108042, "time_dur": 0, "idx": 0}
            ]
        }
    ]
}